plandez/__init__.py
plandez/cache.py
plandez/filters.py
plandez/proj.py
plandez/sources.py
plandez/tests.py
plandez/tiles.py
plandez/util.py
plandez-2.5.1.dev0.dist-info/LICENSE
plandez-2.5.1.dev0.dist-info/METADATA
plandez-2.5.1.dev0.dist-info/WHEEL
plandez-2.5.1.dev0.dist-info/top_level.txt
plandez-2.5.1.dev0.dist-info/RECORD
