Metadata-Version: 2.1
Name: plandez
Version: 2.5.1.dev0
Summary: pLandez is a python toolbox to manipulate map tiles.
Home-page: https://github.com/AhmedElabd96/plandez
Author: Mathieu Leplatre
Author-email: mathieu.leplatre@makina-corpus.com
License: LPGL, see LICENSE file.
Keywords: MBTiles,Mapnik
Platform: UNKNOWN
Classifier: Programming Language :: Python :: 3.5
Classifier: Natural Language :: English
Classifier: Topic :: Utilities
Classifier: Development Status :: 5 - Production/Stable
License-File: LICENSE
Requires-Dist: mbutil
Requires-Dist: requests
Provides-Extra: mapnik
Requires-Dist: Mapnik (>=2.0.0) ; extra == 'mapnik'
Provides-Extra: pil
Requires-Dist: Pillow ; extra == 'pil'
